content_filter/__init__.py
content_filter/check.py
content_filter/filter.py
content_filter/string.py
content_filter/data/filter.json
content_filter/data/replacements.json
tests/__init__.py
tests/custom_file_test.py
tests/custom_filter_test.py
tests/filter_test.py
content_filter-2.2.0.dist-info/LICENSE
content_filter-2.2.0.dist-info/METADATA
content_filter-2.2.0.dist-info/WHEEL
content_filter-2.2.0.dist-info/top_level.txt
content_filter-2.2.0.dist-info/RECORD
