Metadata-Version: 2.1
Name: content-filter
Version: 2.2.0
Summary: A basic but robust content filter for python.
Home-page: https://github.com/MrDogeBro/content_filter
Author: MrDogeBro
License: MIT
Download-URL: https://github.com/MrDogeBro/content_filter/archive/v2.2.0.tar.gz
Platform: UNKNOWN
Classifier: Development Status :: 5 - Production/Stable
Classifier: Natural Language :: English
Classifier: Programming Language :: Python :: 3.6
Classifier: Programming Language :: Python :: 3.7
Classifier: Programming Language :: Python :: 3.8
Classifier: Programming Language :: Python :: 3.9
Classifier: Programming Language :: Python :: 3.10
Classifier: License :: OSI Approved :: MIT License
Classifier: Operating System :: OS Independent
Requires-Python: >=3.6
License-File: LICENSE
